{
	"BUILD_DIR" : "/home/naga/git/simulator/btest/simlib_autogen",
	"CMAKE_BINARY_DIR" : "/home/naga/git/simulator/btest",
	"CMAKE_CURRENT_BINARY_DIR" : "/home/naga/git/simulator/btest",
	"CMAKE_CURRENT_SOURCE_DIR" : "/home/naga/git/simulator",
	"CMAKE_EXECUTABLE" : "/usr/bin/cmake",
	"CMAKE_SOURCE_DIR" : "/home/naga/git/simulator",
	"HEADERS" : 
	[
		[
			"/home/naga/git/simulator/sim/CPU.hpp",
			"MU",
			"ZPZSCMKBGY/moc_CPU.cpp"
		],
		[
			"/home/naga/git/simulator/sim/Compiler.hpp",
			"MU",
			"ZPZSCMKBGY/moc_Compiler.cpp"
		],
		[
			"/home/naga/git/simulator/sim/Memory.hpp",
			"MU",
			"ZPZSCMKBGY/moc_Memory.cpp"
		],
		[
			"/home/naga/git/simulator/sim/Simulator.hpp",
			"MU",
			"ZPZSCMKBGY/moc_Simulator.cpp"
		],
		[
			"/home/naga/git/simulator/sim/fpu.hpp",
			"MU",
			"ZPZSCMKBGY/moc_fpu.cpp"
		]
	],
	"HEADER_EXTENSIONS" : [ "h", "hh", "h++", "hm", "hpp", "hxx", "in", "txx" ],
	"INCLUDE_DIR" : "/home/naga/git/simulator/btest/simlib_autogen/include",
	"MOC_COMPILATION_FILE" : "/home/naga/git/simulator/btest/simlib_autogen/mocs_compilation.cpp",
	"MOC_DEFINITIONS" : [ "QT_NO_KEYWORDS" ],
	"MOC_DEPEND_FILTERS" : 
	[
		[
			"Q_PLUGIN_METADATA",
			"[\n][ \t]*Q_PLUGIN_METADATA[ \t]*\\([^\\)]*FILE[ \t]*\"([^\"]+)\""
		]
	],
	"MOC_INCLUDES" : 
	[
		"/home/naga/git/simulator/btest",
		"/home/naga/git/simulator",
		"/home/naga/git/simulator/include/asmjit/src",
		"/usr/include/c++/9",
		"/usr/include/x86_64-linux-gnu/c++/9",
		"/usr/include/c++/9/backward",
		"/usr/lib/gcc/x86_64-linux-gnu/9/include",
		"/usr/local/include",
		"/usr/include/x86_64-linux-gnu",
		"/usr/include"
	],
	"MOC_MACRO_NAMES" : [ "Q_OBJECT", "Q_GADGET", "Q_NAMESPACE" ],
	"MOC_OPTIONS" : [],
	"MOC_PATH_PREFIX" : true,
	"MOC_PREDEFS_CMD" : 
	[
		"/usr/bin/c++",
		"-dM",
		"-E",
		"-c",
		"/usr/share/cmake-3.16/Modules/CMakeCXXCompilerABI.cpp"
	],
	"MOC_PREDEFS_FILE" : "/home/naga/git/simulator/btest/simlib_autogen/moc_predefs.h",
	"MOC_RELAXED_MODE" : false,
	"MOC_SKIP" : [],
	"MULTI_CONFIG" : false,
	"PARALLEL" : 1,
	"PARSE_CACHE_FILE" : "/home/naga/git/simulator/btest/CMakeFiles/simlib_autogen.dir/ParseCache.txt",
	"QT_MOC_EXECUTABLE" : "/usr/lib/qt5/bin/moc",
	"QT_UIC_EXECUTABLE" : "/usr/lib/qt5/bin/uic",
	"QT_VERSION_MAJOR" : 5,
	"SETTINGS_FILE" : "/home/naga/git/simulator/btest/CMakeFiles/simlib_autogen.dir/AutogenUsed.txt",
	"SOURCES" : 
	[
		[ "/home/naga/git/simulator/sim/CPU.cpp", "MU" ],
		[ "/home/naga/git/simulator/sim/Compiler.cpp", "MU" ],
		[ "/home/naga/git/simulator/sim/Memory.cpp", "MU" ],
		[ "/home/naga/git/simulator/sim/Simulator.cpp", "MU" ],
		[ "/home/naga/git/simulator/sim/fpu.cpp", "MU" ]
	],
	"UIC_OPTIONS" : [],
	"UIC_SEARCH_PATHS" : [],
	"UIC_SKIP" : [],
	"UIC_UI_FILES" : [],
	"VERBOSITY" : 0
}
